Metadata-Version: 1.1
Name: kpkdataapi
Version: 0.0.1
Summary: A very basic calculator
Home-page: UNKNOWN
Author: kpk
Author-email: kpk@kpk.com
License: MIT
Keywords: calculator
Platform: UNKNOWN
Classifier: Development Status :: 5 - Production/Stable
Classifier: Intended Audience :: Education
Classifier: Operating System :: Microsoft :: Windows :: Windows 10
Classifier: License :: OSI Approved :: MIT License
Classifier: Programming Language :: Python :: 3
